[{"task": "boxes", "extra": ["10", "0", "0", "0", "0", "0"], "token": false, "score": 10.0, "user": "B-9", "key": "A150", "time": 1438053690}, {"task": "boxes", "extra": ["10", "10", "0", "0", "0", "0"], "token": false, "score": 20.0, "user": "B-9", "key": "A676", "time": 1438055849}, {"task": "horses", "extra": ["0", "0", "0", "0", "0"], "token": false, "score": 0.0, "user": "B-9", "key": "338", "time": 1438227233}, {"task": "horses", "extra": ["0", "0", "0", "0", "0"], "token": false, "score": 0.0, "user": "B-9", "key": "362", "time": 1438227339}, {"task": "horses", "extra": ["17", "0", "0", "0", "0"], "token": false, "score": 17.0, "user": "B-9", "key": "486", "time": 1438227747}, {"task": "horses", "extra": ["17", "0", "0", "0", "0"], "token": false, "score": 17.0, "user": "B-9", "key": "963", "time": 1438229085}, {"task": "horses", "extra": ["17", "0", "0", "0", "0"], "token": false, "score": 17.0, "user": "B-9", "key": "1081", "time": 1438229349}, {"task": "horses", "extra": ["17", "0", "0", "0", "0"], "token": false, "score": 17.0, "user": "B-9", "key": "1234", "time": 1438229687}, {"task": "horses", "extra": ["17", "0", "0", "0", "0"], "token": false, "score": 17.0, "user": "B-9", "key": "1308", "time": 1438229847}, {"task": "horses", "extra": ["17", "0", "0", "0", "0"], "token": false, "score": 17.0, "user": "B-9", "key": "2063", "time": 1438231744}, {"task": "horses", "extra": ["17", "0", "0", "0", "0"], "token": false, "score": 17.0, "user": "B-9", "key": "2087", "time": 1438231806}, {"task": "horses", "extra": ["17", "0", "0", "0", "0"], "token": false, "score": 17.0, "user": "B-9", "key": "2138", "time": 1438231915}, {"task": "horses", "extra": ["17", "0", "0", "0", "0"], "token": false, "score": 17.0, "user": "B-9", "key": "3260", "time": 1438234362}, {"task": "horses", "extra": ["17", "0", "0", "0", "0"], "token": false, "score": 17.0, "user": "B-9", "key": "3379", "time": 1438234634}, {"task": "horses", "extra": ["17", "0", "0", "0", "0"], "token": false, "score": 17.0, "user": "B-9", "key": "3429", "time": 1438234739}, {"task": "horses", "extra": ["17", "0", "0", "0", "0"], "token": false, "score": 17.0, "user": "B-9", "key": "4126", "time": 1438236158}, {"task": "horses", "extra": ["17", "0", "0", "0", "0"], "token": false, "score": 17.0, "user": "B-9", "key": "4211", "time": 1438236304}, {"task": "horses", "extra": ["17", "0", "0", "0", "0"], "token": false, "score": 17.0, "user": "B-9", "key": "4263", "time": 1438236400}, {"task": "horses", "extra": ["17", "0", "0", "0", "0"], "token": false, "score": 17.0, "user": "B-9", "key": "4303", "time": 1438236469}, {"task": "horses", "extra": ["17", "0", "0", "0", "0"], "token": false, "score": 17.0, "user": "B-9", "key": "4549", "time": 1438236952}, {"task": "horses", "extra": ["17", "0", "0", "0", "0"], "token": false, "score": 17.0, "user": "B-9", "key": "4846", "time": 1438237532}, {"task": "horses", "extra": ["17", "0", "0", "0", "0"], "token": false, "score": 17.0, "user": "B-9", "key": "5047", "time": 1438237895}, {"task": "horses", "extra": ["17", "0", "0", "0", "0"], "token": false, "score": 17.0, "user": "B-9", "key": "5242", "time": 1438238226}, {"task": "horses", "extra": ["0", "0", "0", "0", "0"], "token": false, "score": 0.0, "user": "B-9", "key": "5327", "time": 1438238374}, {"task": "horses", "extra": ["17", "0", "0", "0", "0"], "token": false, "score": 17.0, "user": "B-9", "key": "5373", "time": 1438238457}, {"task": "horses", "extra": ["0", "0", "0", "0", "0"], "token": false, "score": 0.0, "user": "B-9", "key": "5424", "time": 1438238561}, {"task": "horses", "extra": ["17", "0", "0", "0", "0"], "token": false, "score": 17.0, "user": "B-9", "key": "5478", "time": 1438238655}, {"task": "horses", "extra": ["17", "0", "0", "0", "0"], "token": false, "score": 17.0, "user": "B-9", "key": "5527", "time": 1438238767}, {"task": "horses", "extra": ["17", "0", "0", "0", "0"], "token": false, "score": 17.0, "user": "B-9", "key": "5561", "time": 1438238828}, {"task": "horses", "extra": ["17", "0", "0", "0", "0"], "token": false, "score": 17.0, "user": "B-9", "key": "5939", "time": 1438239511}, {"task": "scales", "extra": ["0"], "token": false, "score": 0.0, "user": "B-9", "key": "A1019", "time": 1438057622}, {"task": "scales", "extra": ["0"], "token": false, "score": 0.0, "user": "B-9", "key": "A1149", "time": 1438057960}, {"task": "scales", "extra": ["0"], "token": false, "score": 0.0, "user": "B-9", "key": "A1316", "time": 1438058468}, {"task": "scales", "extra": ["0"], "token": false, "score": 0.0, "user": "B-9", "key": "A1396", "time": 1438058712}, {"task": "scales", "extra": ["0"], "token": false, "score": 0.0, "user": "B-9", "key": "A1496", "time": 1438058947}, {"task": "scales", "extra": ["0"], "token": false, "score": 0.0, "user": "B-9", "key": "A1560", "time": 1438059136}, {"task": "scales", "extra": ["0"], "token": false, "score": 0.0, "user": "B-9", "key": "A1608", "time": 1438059278}, {"task": "scales", "extra": ["0"], "token": false, "score": 0.0, "user": "B-9", "key": "A1632", "time": 1438059341}, {"task": "scales", "extra": ["0"], "token": false, "score": 0.0, "user": "B-9", "key": "A1697", "time": 1438059491}, {"task": "scales", "extra": ["0"], "token": false, "score": 0.0, "user": "B-9", "key": "A1837", "time": 1438059895}, {"task": "scales", "extra": ["0"], "token": false, "score": 0.0, "user": "B-9", "key": "A1863", "time": 1438059956}, {"task": "scales", "extra": ["0"], "token": false, "score": 0.0, "user": "B-9", "key": "A1902", "time": 1438060059}, {"task": "scales", "extra": ["0"], "token": false, "score": 0.0, "user": "B-9", "key": "A1931", "time": 1438060132}, {"task": "scales", "extra": ["0"], "token": false, "score": 0.0, "user": "B-9", "key": "A2005", "time": 1438060337}, {"task": "scales", "extra": ["0"], "token": false, "score": 0.0, "user": "B-9", "key": "A2106", "time": 1438060652}, {"task": "scales", "extra": ["19.57"], "token": false, "score": 19.57, "user": "B-9", "key": "A2945", "time": 1438062847}, {"task": "scales", "extra": ["19.52"], "token": false, "score": 19.52, "user": "B-9", "key": "A4064", "time": 1438066465}, {"task": "scales", "extra": ["19.43"], "token": false, "score": 19.43, "user": "B-9", "key": "A4352", "time": 1438067579}, {"task": "sorting", "extra": ["8", "12", "0", "0", "0", "0"], "token": false, "score": 20.0, "user": "B-9", "key": "1535", "time": 1438230433}, {"task": "sorting", "extra": ["8", "12", "16", "0", "0", "0"], "token": false, "score": 36.0, "user": "B-9", "key": "1860", "time": 1438231291}, {"task": "teams", "extra": ["0", "0", "0", "0"], "token": false, "score": 0.0, "user": "B-9", "key": "A3490", "time": 1438064385}, {"task": "teams", "extra": ["0", "0", "0", "0"], "token": false, "score": 0.0, "user": "B-9", "key": "A3774", "time": 1438065612}, {"task": "teams", "extra": ["0", "0", "0", "0"], "token": false, "score": 0.0, "user": "B-9", "key": "A3928", "time": 1438066036}, {"task": "teams", "extra": ["0", "0", "0", "0"], "token": false, "score": 0.0, "user": "B-9", "key": "A4546", "time": 1438068286}, {"task": "teams", "extra": ["0", "0", "0", "0"], "token": false, "score": 0.0, "user": "B-9", "key": "A4736", "time": 1438068915}, {"task": "teams", "extra": ["0", "0", "0", "0"], "token": false, "score": 0.0, "user": "B-9", "key": "A4962", "time": 1438069683}, {"task": "teams", "extra": ["0", "0", "0", "0"], "token": false, "score": 0.0, "user": "B-9", "key": "A5072", "time": 1438069922}, {"task": "towns", "extra": ["0", "0", "0", "0", "0", "0"], "token": false, "score": 0.0, "user": "B-9", "key": "7120", "time": 1438241527}, {"task": "towns", "extra": ["0", "0", "0", "0", "0", "0"], "token": false, "score": 0.0, "user": "B-9", "key": "7172", "time": 1438241610}, {"task": "towns", "extra": ["0", "0", "0", "0", "0", "0"], "token": false, "score": 0.0, "user": "B-9", "key": "7842", "time": 1438242499}, {"task": "towns", "extra": ["0", "0", "0", "0", "0", "0"], "token": false, "score": 0.0, "user": "B-9", "key": "7993", "time": 1438242676}, {"task": "towns", "extra": ["0", "0", "0", "0", "0", "0"], "token": false, "score": 0.0, "user": "B-9", "key": "8053", "time": 1438242745}, {"task": "towns", "extra": ["0", "0", "0", "0", "0", "0"], "token": false, "score": 0.0, "user": "B-9", "key": "8114", "time": 1438242806}, {"task": "towns", "extra": ["0", "0", "0", "0", "0", "0"], "token": false, "score": 0.0, "user": "B-9", "key": "8177", "time": 1438242870}]