[{"task": "boxes", "extra": ["0", "0", "0", "0", "0", "0"], "token": false, "score": 0.0, "user": "F-24", "key": "A388", "time": 1438054848}, {"task": "boxes", "extra": ["0", "10", "0", "0", "0", "0"], "token": false, "score": 10.0, "user": "F-24", "key": "A1188", "time": 1438058089}, {"task": "boxes", "extra": ["0", "10", "0", "0", "0", "0"], "token": false, "score": 10.0, "user": "F-24", "key": "A2900", "time": 1438062738}, {"task": "boxes", "extra": ["0", "10", "0", "0", "0", "0"], "token": false, "score": 10.0, "user": "F-24", "key": "A3019", "time": 1438063047}, {"task": "boxes", "extra": ["0", "10", "0", "0", "0", "0"], "token": false, "score": 10.0, "user": "F-24", "key": "A3262", "time": 1438063698}, {"task": "boxes", "extra": ["0", "10", "0", "0", "0", "0"], "token": false, "score": 10.0, "user": "F-24", "key": "A3699", "time": 1438065461}, {"task": "boxes", "extra": ["0", "10", "0", "0", "0", "0"], "token": false, "score": 10.0, "user": "F-24", "key": "A3995", "time": 1438066217}, {"task": "boxes", "extra": ["0", "10", "0", "0", "0", "0"], "token": false, "score": 10.0, "user": "F-24", "key": "A4221", "time": 1438067156}, {"task": "boxes", "extra": ["0", "0", "0", "0", "0", "0"], "token": false, "score": 0.0, "user": "F-24", "key": "A4315", "time": 1438067461}, {"task": "boxes", "extra": ["0", "10", "0", "0", "0", "0"], "token": false, "score": 10.0, "user": "F-24", "key": "A4577", "time": 1438068419}, {"task": "boxes", "extra": ["0", "10", "0", "0", "0", "0"], "token": false, "score": 10.0, "user": "F-24", "key": "A4888", "time": 1438069425}, {"task": "horses", "extra": ["0", "0", "0", "0", "0"], "token": false, "score": 0.0, "user": "F-24", "key": "3923", "time": 1438235750}, {"task": "horses", "extra": ["0", "0", "0", "0", "0"], "token": false, "score": 0.0, "user": "F-24", "key": "4398", "time": 1438236670}, {"task": "horses", "extra": ["0", "0", "0", "0", "0"], "token": false, "score": 0.0, "user": "F-24", "key": "4803", "time": 1438237459}, {"task": "horses", "extra": ["0", "0", "0", "0", "0"], "token": false, "score": 0.0, "user": "F-24", "key": "4848", "time": 1438237532}, {"task": "horses", "extra": ["0", "0", "0", "0", "0"], "token": false, "score": 0.0, "user": "F-24", "key": "4959", "time": 1438237731}, {"task": "sorting", "extra": ["0", "0", "0", "0", "0", "0"], "token": false, "score": 0.0, "user": "F-24", "key": "516", "time": 1438227813}, {"task": "sorting", "extra": ["0", "0", "0", "0", "0", "0"], "token": false, "score": 0.0, "user": "F-24", "key": "608", "time": 1438228093}, {"task": "sorting", "extra": ["0", "0", "0", "0", "0", "0"], "token": false, "score": 0.0, "user": "F-24", "key": "639", "time": 1438228168}, {"task": "sorting", "extra": ["0", "0", "0", "0", "0", "0"], "token": false, "score": 0.0, "user": "F-24", "key": "746", "time": 1438228530}, {"task": "sorting", "extra": ["8", "12", "0", "0", "0", "0"], "token": false, "score": 20.0, "user": "F-24", "key": "786", "time": 1438228612}, {"task": "sorting", "extra": ["8", "0", "0", "0", "0", "0"], "token": false, "score": 8.0, "user": "F-24", "key": "830", "time": 1438228739}, {"task": "sorting", "extra": ["8", "12", "0", "0", "0", "0"], "token": false, "score": 20.0, "user": "F-24", "key": "880", "time": 1438228870}, {"task": "sorting", "extra": ["8", "12", "16", "0", "0", "0"], "token": false, "score": 36.0, "user": "F-24", "key": "1949", "time": 1438231494}, {"task": "sorting", "extra": ["8", "12", "16", "0", "0", "0"], "token": false, "score": 36.0, "user": "F-24", "key": "2126", "time": 1438231888}, {"task": "sorting", "extra": ["8", "12", "16", "0", "0", "0"], "token": false, "score": 36.0, "user": "F-24", "key": "2163", "time": 1438231961}, {"task": "sorting", "extra": ["8", "12", "16", "0", "0", "0"], "token": false, "score": 36.0, "user": "F-24", "key": "2425", "time": 1438232572}, {"task": "sorting", "extra": ["8", "12", "16", "0", "0", "0"], "token": false, "score": 36.0, "user": "F-24", "key": "2573", "time": 1438232923}, {"task": "sorting", "extra": ["8", "12", "16", "0", "0", "0"], "token": false, "score": 36.0, "user": "F-24", "key": "2936", "time": 1438233667}]