[{"task": "boxes", "extra": ["10", "0", "0", "0", "0", "0"], "token": false, "score": 10.0, "user": "i-12", "key": "A828", "time": 1438056760}, {"task": "boxes", "extra": ["10", "10", "15", "0", "0", "0"], "token": false, "score": 35.0, "user": "i-12", "key": "A1161", "time": 1438058015}, {"task": "boxes", "extra": ["10", "0", "0", "0", "0", "0"], "token": false, "score": 10.0, "user": "i-12", "key": "A1282", "time": 1438058395}, {"task": "boxes", "extra": ["10", "10", "15", "0", "0", "0"], "token": false, "score": 35.0, "user": "i-12", "key": "A3428", "time": 1438064119}, {"task": "boxes", "extra": ["0", "0", "0", "0", "0", "0"], "token": false, "score": 0.0, "user": "i-12", "key": "A3579", "time": 1438064705}, {"task": "boxes", "extra": ["10", "10", "15", "15", "0", "0"], "token": false, "score": 50.0, "user": "i-12", "key": "A3882", "time": 1438065903}, {"task": "boxes", "extra": ["0", "0", "0", "0", "0", "0"], "token": false, "score": 0.0, "user": "i-12", "key": "A3946", "time": 1438066072}, {"task": "boxes", "extra": ["10", "10", "15", "0", "0", "0"], "token": false, "score": 35.0, "user": "i-12", "key": "A3972", "time": 1438066150}, {"task": "boxes", "extra": ["0", "0", "0", "0", "0", "0"], "token": false, "score": 0.0, "user": "i-12", "key": "A4407", "time": 1438067780}, {"task": "boxes", "extra": ["0", "10", "0", "0", "0", "0"], "token": false, "score": 10.0, "user": "i-12", "key": "A4560", "time": 1438068347}, {"task": "boxes", "extra": ["0", "0", "0", "0", "0", "0"], "token": false, "score": 0.0, "user": "i-12", "key": "A4770", "time": 1438069045}, {"task": "boxes", "extra": ["0", "10", "0", "0", "0", "0"], "token": false, "score": 10.0, "user": "i-12", "key": "A4861", "time": 1438069350}, {"task": "boxes", "extra": ["10", "10", "15", "0", "0", "0"], "token": false, "score": 35.0, "user": "i-12", "key": "A5010", "time": 1438069818}, {"task": "boxes", "extra": ["10", "10", "15", "0", "0", "0"], "token": false, "score": 35.0, "user": "i-12", "key": "A5206", "time": 1438070129}, {"task": "horses", "extra": ["17", "0", "0", "0", "0"], "token": false, "score": 17.0, "user": "i-12", "key": "219", "time": 1438226548}, {"task": "horses", "extra": ["0", "0", "0", "0", "0"], "token": false, "score": 0.0, "user": "i-12", "key": "885", "time": 1438228886}, {"task": "horses", "extra": ["0", "0", "0", "0", "0"], "token": false, "score": 0.0, "user": "i-12", "key": "921", "time": 1438228990}, {"task": "horses", "extra": ["17", "17", "20", "0", "0"], "token": false, "score": 54.0, "user": "i-12", "key": "1047", "time": 1438229274}, {"task": "horses", "extra": ["17", "17", "0", "23", "0"], "token": false, "score": 57.0, "user": "i-12", "key": "1120", "time": 1438229448}, {"task": "horses", "extra": ["17", "17", "0", "23", "0"], "token": false, "score": 57.0, "user": "i-12", "key": "1206", "time": 1438229637}, {"task": "horses", "extra": ["17", "17", "20", "23", "23"], "token": false, "score": 100.0, "user": "i-12", "key": "1248", "time": 1438229714}, {"task": "horses", "extra": ["17", "17", "0", "23", "0"], "token": false, "score": 57.0, "user": "i-12", "key": "1853", "time": 1438231280}, {"task": "horses", "extra": ["17", "0", "0", "0", "0"], "token": false, "score": 17.0, "user": "i-12", "key": "2018", "time": 1438231640}, {"task": "horses", "extra": ["17", "17", "0", "23", "0"], "token": false, "score": 57.0, "user": "i-12", "key": "2118", "time": 1438231875}, {"task": "horses", "extra": ["17", "17", "20", "23", "23"], "token": false, "score": 100.0, "user": "i-12", "key": "2164", "time": 1438231963}, {"task": "horses", "extra": ["17", "17", "0", "23", "0"], "token": false, "score": 57.0, "user": "i-12", "key": "6960", "time": 1438241282}, {"task": "horses", "extra": ["17", "17", "20", "23", "23"], "token": false, "score": 100.0, "user": "i-12", "key": "7003", "time": 1438241364}, {"task": "scales", "extra": ["45.45"], "token": false, "score": 45.45, "user": "i-12", "key": "A4330", "time": 1438067516}, {"task": "scales", "extra": ["45.45"], "token": false, "score": 45.45, "user": "i-12", "key": "A4618", "time": 1438068548}, {"task": "sorting", "extra": ["8", "12", "0", "0", "0", "0"], "token": false, "score": 20.0, "user": "i-12", "key": "2324", "time": 1438232329}, {"task": "sorting", "extra": ["8", "12", "0", "0", "0", "0"], "token": false, "score": 20.0, "user": "i-12", "key": "2837", "time": 1438233486}, {"task": "sorting", "extra": ["8", "12", "16", "0", "0", "0"], "token": false, "score": 36.0, "user": "i-12", "key": "2884", "time": 1438233570}, {"task": "sorting", "extra": ["8", "12", "0", "0", "0", "0"], "token": false, "score": 20.0, "user": "i-12", "key": "2920", "time": 1438233632}, {"task": "sorting", "extra": ["8", "12", "16", "0", "0", "0"], "token": false, "score": 36.0, "user": "i-12", "key": "2998", "time": 1438233802}, {"task": "sorting", "extra": ["8", "12", "16", "0", "0", "0"], "token": false, "score": 36.0, "user": "i-12", "key": "3046", "time": 1438233887}, {"task": "sorting", "extra": ["8", "12", "0", "0", "0", "0"], "token": false, "score": 20.0, "user": "i-12", "key": "5040", "time": 1438237888}, {"task": "sorting", "extra": ["8", "12", "0", "0", "0", "0"], "token": false, "score": 20.0, "user": "i-12", "key": "5312", "time": 1438238348}, {"task": "sorting", "extra": ["8", "12", "0", "0", "0", "0"], "token": false, "score": 20.0, "user": "i-12", "key": "5380", "time": 1438238471}, {"task": "sorting", "extra": ["8", "12", "0", "0", "0", "0"], "token": false, "score": 20.0, "user": "i-12", "key": "5436", "time": 1438238583}, {"task": "sorting", "extra": ["8", "12", "0", "0", "0", "0"], "token": false, "score": 20.0, "user": "i-12", "key": "5493", "time": 1438238686}, {"task": "sorting", "extra": ["0", "0", "0", "0", "0", "0"], "token": false, "score": 0.0, "user": "i-12", "key": "5550", "time": 1438238809}, {"task": "sorting", "extra": ["8", "12", "0", "0", "0", "0"], "token": false, "score": 20.0, "user": "i-12", "key": "5592", "time": 1438238869}, {"task": "sorting", "extra": ["8", "12", "16", "18", "0", "0"], "token": false, "score": 54.0, "user": "i-12", "key": "5664", "time": 1438239006}, {"task": "sorting", "extra": ["8", "12", "0", "0", "0", "0"], "token": false, "score": 20.0, "user": "i-12", "key": "5820", "time": 1438239288}, {"task": "sorting", "extra": ["8", "12", "0", "0", "0", "0"], "token": false, "score": 20.0, "user": "i-12", "key": "5856", "time": 1438239356}, {"task": "sorting", "extra": ["8", "12", "16", "18", "0", "0"], "token": false, "score": 54.0, "user": "i-12", "key": "5888", "time": 1438239417}, {"task": "sorting", "extra": ["8", "12", "0", "0", "0", "0"], "token": false, "score": 20.0, "user": "i-12", "key": "5982", "time": 1438239611}, {"task": "sorting", "extra": ["8", "12", "16", "18", "20", "0"], "token": false, "score": 74.0, "user": "i-12", "key": "6243", "time": 1438240107}, {"task": "sorting", "extra": ["8", "12", "16", "18", "20", "0"], "token": false, "score": 74.0, "user": "i-12", "key": "7614", "time": 1438242218}, {"task": "teams", "extra": ["0", "0", "0", "0"], "token": false, "score": 0.0, "user": "i-12", "key": "A674", "time": 1438055841}, {"task": "teams", "extra": ["0", "0", "0", "0"], "token": false, "score": 0.0, "user": "i-12", "key": "A1247", "time": 1438058278}, {"task": "teams", "extra": ["0", "0", "0", "0"], "token": false, "score": 0.0, "user": "i-12", "key": "A1504", "time": 1438058957}, {"task": "teams", "extra": ["21", "13", "0", "0"], "token": false, "score": 34.0, "user": "i-12", "key": "A1724", "time": 1438059568}, {"task": "teams", "extra": ["0", "0", "0", "0"], "token": false, "score": 0.0, "user": "i-12", "key": "A1927", "time": 1438060117}, {"task": "teams", "extra": ["0", "0", "0", "0"], "token": false, "score": 0.0, "user": "i-12", "key": "A2007", "time": 1438060342}, {"task": "teams", "extra": ["21", "13", "0", "0"], "token": false, "score": 34.0, "user": "i-12", "key": "A2205", "time": 1438060959}, {"task": "teams", "extra": ["21", "13", "0", "0"], "token": false, "score": 34.0, "user": "i-12", "key": "A2316", "time": 1438061220}, {"task": "teams", "extra": ["21", "13", "0", "0"], "token": false, "score": 34.0, "user": "i-12", "key": "A2353", "time": 1438061322}, {"task": "teams", "extra": ["21", "13", "0", "0"], "token": false, "score": 34.0, "user": "i-12", "key": "A2411", "time": 1438061494}, {"task": "teams", "extra": ["21", "13", "0", "0"], "token": false, "score": 34.0, "user": "i-12", "key": "A2594", "time": 1438061980}, {"task": "teams", "extra": ["21", "13", "0", "0"], "token": false, "score": 34.0, "user": "i-12", "key": "A2864", "time": 1438062631}, {"task": "teams", "extra": ["21", "0", "0", "0"], "token": false, "score": 21.0, "user": "i-12", "key": "A2954", "time": 1438062882}, {"task": "teams", "extra": ["21", "13", "0", "0"], "token": false, "score": 34.0, "user": "i-12", "key": "A2978", "time": 1438062945}, {"task": "teams", "extra": ["21", "13", "0", "0"], "token": false, "score": 34.0, "user": "i-12", "key": "A3060", "time": 1438063143}, {"task": "teams", "extra": ["21", "13", "0", "0"], "token": false, "score": 34.0, "user": "i-12", "key": "A3106", "time": 1438063296}, {"task": "teams", "extra": ["21", "0", "0", "0"], "token": false, "score": 21.0, "user": "i-12", "key": "A3183", "time": 1438063498}, {"task": "teams", "extra": ["21", "13", "0", "0"], "token": false, "score": 34.0, "user": "i-12", "key": "A3383", "time": 1438063998}, {"task": "teams", "extra": ["0", "0", "0", "0"], "token": false, "score": 0.0, "user": "i-12", "key": "A3486", "time": 1438064364}, {"task": "teams", "extra": ["0", "0", "0", "0"], "token": false, "score": 0.0, "user": "i-12", "key": "A3631", "time": 1438064859}, {"task": "teams", "extra": ["21", "13", "43", "0"], "token": false, "score": 77.0, "user": "i-12", "key": "A3901", "time": 1438065937}, {"task": "teams", "extra": ["21", "13", "43", "0"], "token": false, "score": 77.0, "user": "i-12", "key": "A4468", "time": 1438068029}]