[{"task": "boxes", "extra": ["10", "0", "0", "0", "0", "0"], "token": false, "score": 10.0, "user": "O-12", "key": "A157", "time": 1438053756}, {"task": "boxes", "extra": ["10", "0", "0", "0", "0", "0"], "token": false, "score": 10.0, "user": "O-12", "key": "A180", "time": 1438053922}, {"task": "boxes", "extra": ["10", "0", "0", "0", "0", "0"], "token": false, "score": 10.0, "user": "O-12", "key": "A206", "time": 1438054090}, {"task": "boxes", "extra": ["10", "0", "0", "0", "0", "0"], "token": false, "score": 10.0, "user": "O-12", "key": "A237", "time": 1438054239}, {"task": "boxes", "extra": ["10", "0", "0", "0", "0", "0"], "token": false, "score": 10.0, "user": "O-12", "key": "A273", "time": 1438054386}, {"task": "boxes", "extra": ["10", "0", "0", "0", "0", "0"], "token": false, "score": 10.0, "user": "O-12", "key": "A294", "time": 1438054467}, {"task": "boxes", "extra": ["10", "0", "0", "0", "0", "0"], "token": false, "score": 10.0, "user": "O-12", "key": "A346", "time": 1438054670}, {"task": "boxes", "extra": ["10", "0", "0", "0", "0", "0"], "token": false, "score": 10.0, "user": "O-12", "key": "A418", "time": 1438054944}, {"task": "boxes", "extra": ["10", "0", "0", "0", "0", "0"], "token": false, "score": 10.0, "user": "O-12", "key": "A532", "time": 1438055357}, {"task": "boxes", "extra": ["10", "0", "0", "0", "0", "0"], "token": false, "score": 10.0, "user": "O-12", "key": "A567", "time": 1438055506}, {"task": "boxes", "extra": ["10", "0", "0", "0", "0", "0"], "token": false, "score": 10.0, "user": "O-12", "key": "A631", "time": 1438055678}, {"task": "boxes", "extra": ["10", "10", "0", "0", "0", "0"], "token": false, "score": 20.0, "user": "O-12", "key": "A936", "time": 1438057357}, {"task": "horses", "extra": ["17", "0", "0", "0", "0"], "token": false, "score": 17.0, "user": "O-12", "key": "417", "time": 1438227526}, {"task": "horses", "extra": ["17", "0", "0", "0", "0"], "token": false, "score": 17.0, "user": "O-12", "key": "446", "time": 1438227640}, {"task": "horses", "extra": ["17", "0", "0", "0", "0"], "token": false, "score": 17.0, "user": "O-12", "key": "497", "time": 1438227764}, {"task": "scales", "extra": ["0"], "token": false, "score": 0.0, "user": "O-12", "key": "A3519", "time": 1438064474}, {"task": "scales", "extra": ["0"], "token": false, "score": 0.0, "user": "O-12", "key": "A3706", "time": 1438065468}, {"task": "scales", "extra": ["71.42"], "token": false, "score": 71.42, "user": "O-12", "key": "A4075", "time": 1438066506}, {"task": "sorting", "extra": ["8", "12", "0", "0", "0", "0"], "token": false, "score": 20.0, "user": "O-12", "key": "248", "time": 1438226794}, {"task": "sorting", "extra": ["0", "0", "0", "0", "0", "0"], "token": false, "score": 0.0, "user": "O-12", "key": "4847", "time": 1438237532}, {"task": "sorting", "extra": ["0", "0", "0", "0", "0", "0"], "token": false, "score": 0.0, "user": "O-12", "key": "4890", "time": 1438237607}, {"task": "sorting", "extra": ["8", "12", "16", "0", "0", "0"], "token": false, "score": 36.0, "user": "O-12", "key": "5308", "time": 1438238342}, {"task": "sorting", "extra": ["8", "12", "16", "0", "0", "0"], "token": false, "score": 36.0, "user": "O-12", "key": "5393", "time": 1438238499}, {"task": "sorting", "extra": ["8", "12", "16", "0", "0", "0"], "token": false, "score": 36.0, "user": "O-12", "key": "5458", "time": 1438238616}, {"task": "sorting", "extra": ["8", "12", "16", "18", "20", "0"], "token": false, "score": 74.0, "user": "O-12", "key": "6232", "time": 1438240084}, {"task": "sorting", "extra": ["8", "12", "16", "18", "20", "26"], "token": false, "score": 100.0, "user": "O-12", "key": "6344", "time": 1438240295}, {"task": "teams", "extra": ["0", "0", "0", "0"], "token": false, "score": 0.0, "user": "O-12", "key": "A2062", "time": 1438060525}, {"task": "teams", "extra": ["0", "0", "0", "0"], "token": false, "score": 0.0, "user": "O-12", "key": "A2292", "time": 1438061172}, {"task": "teams", "extra": ["0", "0", "0", "0"], "token": false, "score": 0.0, "user": "O-12", "key": "A2434", "time": 1438061557}, {"task": "teams", "extra": ["0", "0", "0", "0"], "token": false, "score": 0.0, "user": "O-12", "key": "A2460", "time": 1438061629}, {"task": "teams", "extra": ["0", "0", "0", "0"], "token": false, "score": 0.0, "user": "O-12", "key": "A3819", "time": 1438065707}, {"task": "teams", "extra": ["0", "0", "0", "0"], "token": false, "score": 0.0, "user": "O-12", "key": "A4616", "time": 1438068545}, {"task": "teams", "extra": ["0", "0", "0", "0"], "token": false, "score": 0.0, "user": "O-12", "key": "A5023", "time": 1438069845}, {"task": "teams", "extra": ["0", "0", "0", "0"], "token": false, "score": 0.0, "user": "O-12", "key": "A5193", "time": 1438070113}, {"task": "towns", "extra": ["0", "0", "0", "0", "0", "0"], "token": false, "score": 0.0, "user": "O-12", "key": "1749", "time": 1438231029}, {"task": "towns", "extra": ["0", "0", "0", "0", "0", "0"], "token": false, "score": 0.0, "user": "O-12", "key": "1775", "time": 1438231090}, {"task": "towns", "extra": ["0", "0", "0", "0", "0", "0"], "token": false, "score": 0.0, "user": "O-12", "key": "2005", "time": 1438231607}, {"task": "towns", "extra": ["0", "0", "0", "0", "0", "0"], "token": false, "score": 0.0, "user": "O-12", "key": "2143", "time": 1438231924}, {"task": "towns", "extra": ["0", "0", "0", "0", "0", "0"], "token": false, "score": 0.0, "user": "O-12", "key": "7287", "time": 1438241765}, {"task": "towns", "extra": ["0", "0", "0", "0", "0", "0"], "token": false, "score": 0.0, "user": "O-12", "key": "7973", "time": 1438242659}]