[{"task": "boxes", "extra": ["0", "0", "0", "0", "0", "0"], "token": false, "score": 0.0, "user": "O-6", "key": "A220", "time": 1438054175}, {"task": "boxes", "extra": ["0", "0", "0", "0", "0", "0"], "token": false, "score": 0.0, "user": "O-6", "key": "A331", "time": 1438054609}, {"task": "boxes", "extra": ["0", "0", "0", "0", "0", "0"], "token": false, "score": 0.0, "user": "O-6", "key": "A901", "time": 1438057217}, {"task": "boxes", "extra": ["0", "0", "0", "0", "0", "0"], "token": false, "score": 0.0, "user": "O-6", "key": "A2212", "time": 1438060991}, {"task": "boxes", "extra": ["0", "0", "0", "0", "0", "0"], "token": false, "score": 0.0, "user": "O-6", "key": "A2259", "time": 1438061081}, {"task": "boxes", "extra": ["0", "0", "0", "0", "0", "0"], "token": false, "score": 0.0, "user": "O-6", "key": "A2281", "time": 1438061149}, {"task": "boxes", "extra": ["0", "0", "0", "0", "0", "0"], "token": false, "score": 0.0, "user": "O-6", "key": "A2350", "time": 1438061309}, {"task": "boxes", "extra": ["0", "0", "0", "0", "0", "0"], "token": false, "score": 0.0, "user": "O-6", "key": "A2809", "time": 1438062514}, {"task": "boxes", "extra": ["10", "0", "0", "0", "0", "0"], "token": false, "score": 10.0, "user": "O-6", "key": "A2911", "time": 1438062769}, {"task": "boxes", "extra": ["0", "0", "0", "0", "0", "0"], "token": false, "score": 0.0, "user": "O-6", "key": "A2998", "time": 1438063005}, {"task": "boxes", "extra": ["10", "0", "0", "0", "0", "0"], "token": false, "score": 10.0, "user": "O-6", "key": "A3048", "time": 1438063108}, {"task": "boxes", "extra": ["10", "0", "0", "0", "0", "0"], "token": false, "score": 10.0, "user": "O-6", "key": "A3124", "time": 1438063341}, {"task": "boxes", "extra": ["10", "0", "0", "0", "0", "0"], "token": false, "score": 10.0, "user": "O-6", "key": "A3729", "time": 1438065529}, {"task": "boxes", "extra": ["10", "10", "0", "0", "0", "0"], "token": false, "score": 20.0, "user": "O-6", "key": "A3808", "time": 1438065681}, {"task": "boxes", "extra": ["10", "10", "0", "0", "0", "0"], "token": false, "score": 20.0, "user": "O-6", "key": "A4413", "time": 1438067803}, {"task": "boxes", "extra": ["10", "10", "0", "0", "0", "0"], "token": false, "score": 20.0, "user": "O-6", "key": "A5329", "time": 1438070301}, {"task": "horses", "extra": ["0", "0", "0", "0", "0"], "token": false, "score": 0.0, "user": "O-6", "key": "204", "time": 1438226339}, {"task": "horses", "extra": ["17", "0", "0", "0", "0"], "token": false, "score": 17.0, "user": "O-6", "key": "212", "time": 1438226445}, {"task": "horses", "extra": ["17", "0", "0", "0", "0"], "token": false, "score": 17.0, "user": "O-6", "key": "246", "time": 1438226787}, {"task": "horses", "extra": ["17", "0", "0", "0", "0"], "token": false, "score": 17.0, "user": "O-6", "key": "322", "time": 1438227140}, {"task": "horses", "extra": ["17", "0", "0", "0", "0"], "token": false, "score": 17.0, "user": "O-6", "key": "816", "time": 1438228703}, {"task": "horses", "extra": ["17", "0", "0", "0", "0"], "token": false, "score": 17.0, "user": "O-6", "key": "923", "time": 1438228996}, {"task": "horses", "extra": ["17", "17", "0", "0", "0"], "token": false, "score": 34.0, "user": "O-6", "key": "1269", "time": 1438229761}, {"task": "horses", "extra": ["0", "0", "0", "0", "0"], "token": false, "score": 0.0, "user": "O-6", "key": "1394", "time": 1438230059}, {"task": "horses", "extra": ["17", "0", "0", "0", "0"], "token": false, "score": 17.0, "user": "O-6", "key": "1420", "time": 1438230136}, {"task": "horses", "extra": ["17", "0", "0", "0", "0"], "token": false, "score": 17.0, "user": "O-6", "key": "1445", "time": 1438230202}, {"task": "horses", "extra": ["17", "0", "0", "0", "0"], "token": false, "score": 17.0, "user": "O-6", "key": "1463", "time": 1438230263}, {"task": "horses", "extra": ["17", "0", "0", "0", "0"], "token": false, "score": 17.0, "user": "O-6", "key": "1501", "time": 1438230353}, {"task": "horses", "extra": ["17", "17", "0", "0", "0"], "token": false, "score": 34.0, "user": "O-6", "key": "1530", "time": 1438230414}, {"task": "horses", "extra": ["0", "0", "0", "0", "0"], "token": false, "score": 0.0, "user": "O-6", "key": "6521", "time": 1438240583}, {"task": "horses", "extra": ["17", "0", "0", "0", "0"], "token": false, "score": 17.0, "user": "O-6", "key": "6563", "time": 1438240657}, {"task": "horses", "extra": ["17", "17", "0", "0", "0"], "token": false, "score": 34.0, "user": "O-6", "key": "6607", "time": 1438240721}, {"task": "horses", "extra": ["17", "17", "0", "0", "0"], "token": false, "score": 34.0, "user": "O-6", "key": "6727", "time": 1438240914}, {"task": "horses", "extra": ["0", "0", "0", "0", "0"], "token": false, "score": 0.0, "user": "O-6", "key": "6767", "time": 1438240980}, {"task": "horses", "extra": ["0", "0", "0", "0", "0"], "token": false, "score": 0.0, "user": "O-6", "key": "6881", "time": 1438241150}, {"task": "horses", "extra": ["17", "0", "0", "0", "0"], "token": false, "score": 17.0, "user": "O-6", "key": "7077", "time": 1438241465}, {"task": "horses", "extra": ["17", "17", "0", "0", "0"], "token": false, "score": 34.0, "user": "O-6", "key": "7122", "time": 1438241529}, {"task": "horses", "extra": ["17", "0", "0", "0", "0"], "token": false, "score": 17.0, "user": "O-6", "key": "7268", "time": 1438241741}, {"task": "horses", "extra": ["17", "17", "0", "0", "0"], "token": false, "score": 34.0, "user": "O-6", "key": "7372", "time": 1438241889}, {"task": "horses", "extra": ["17", "0", "0", "0", "0"], "token": false, "score": 17.0, "user": "O-6", "key": "7872", "time": 1438242545}, {"task": "horses", "extra": ["17", "0", "0", "0", "0"], "token": false, "score": 17.0, "user": "O-6", "key": "7934", "time": 1438242619}, {"task": "horses", "extra": ["17", "0", "0", "0", "0"], "token": false, "score": 17.0, "user": "O-6", "key": "8023", "time": 1438242713}, {"task": "horses", "extra": ["17", "0", "0", "0", "0"], "token": false, "score": 17.0, "user": "O-6", "key": "8194", "time": 1438242892}, {"task": "horses", "extra": ["17", "0", "0", "0", "0"], "token": false, "score": 17.0, "user": "O-6", "key": "8279", "time": 1438242973}, {"task": "horses", "extra": ["17", "17", "0", "0", "0"], "token": false, "score": 34.0, "user": "O-6", "key": "8344", "time": 1438243045}, {"task": "horses", "extra": ["17", "0", "0", "0", "0"], "token": false, "score": 17.0, "user": "O-6", "key": "8418", "time": 1438243107}, {"task": "horses", "extra": ["17", "17", "0", "0", "0"], "token": false, "score": 34.0, "user": "O-6", "key": "8507", "time": 1438243173}, {"task": "scales", "extra": ["0"], "token": false, "score": 0.0, "user": "O-6", "key": "A4354", "time": 1438067584}, {"task": "scales", "extra": ["0"], "token": false, "score": 0.0, "user": "O-6", "key": "A4492", "time": 1438068106}, {"task": "scales", "extra": ["0"], "token": false, "score": 0.0, "user": "O-6", "key": "A4580", "time": 1438068433}, {"task": "sorting", "extra": ["0", "0", "0", "0", "0", "0"], "token": false, "score": 0.0, "user": "O-6", "key": "1980", "time": 1438231548}, {"task": "sorting", "extra": ["8", "12", "0", "0", "0", "0"], "token": false, "score": 20.0, "user": "O-6", "key": "2157", "time": 1438231949}, {"task": "towns", "extra": ["0", "0", "0", "0", "0", "0"], "token": false, "score": 0.0, "user": "O-6", "key": "3451", "time": 1438234780}]